MASA.cp39-win_amd64.pyd
MASA-1.4.dist-info/LICENSE.txt
MASA-1.4.dist-info/METADATA
MASA-1.4.dist-info/WHEEL
MASA-1.4.dist-info/top_level.txt
MASA-1.4.dist-info/RECORD
