Metadata-Version: 2.1
Name: MASA
Version: 1.4
Summary: Statistical package focused on linear regression and statistical testing.
Home-page: https://github.com/nick12221/Mathematical-and-Statistical-Analytics
Author: Nick Pettit
Author-email: nickpettit12321@gmail.com
License: MIT
Project-URL: Source Code, https://github.com/nick12221/Mathematical-and-Statistical-Analytics
Platform: UNKNOWN
License-File: LICENSE.txt
Requires-Dist: PyObjC ; platform_system == "Darwin"
Requires-Dist: PyGObject ; platform_system == "Linux"
